setup.py
i3pystatus_anybar/__init__.py
i3pystatus_anybar.egg-info/PKG-INFO
i3pystatus_anybar.egg-info/SOURCES.txt
i3pystatus_anybar.egg-info/dependency_links.txt
i3pystatus_anybar.egg-info/requires.txt
i3pystatus_anybar.egg-info/top_level.txt
i3pystatus_anybar.egg-info/zip-safe