Metadata-Version: 1.1
Name: i3pystatus-anybar
Version: 1.0
Summary: AnyBar widget for i3pystatus
Home-page: http://github.com/narma/i3pystatus-anybar
Author: UNKNOWN
Author-email: UNKNOWN
License: MIT
Platform: UNKNOWN
Classifier: Development Status :: 4 - Beta
Classifier: Environment :: X11 Applications
Classifier: License :: OSI Approved :: MIT License
Classifier: Operating System :: POSIX :: Linux
Classifier: Programming Language :: Python :: 3
Classifier: Topic :: Desktop Environment :: Window Managers
